pytch/__init__.py
pytch/__main__.py
pytch/binder.py
pytch/codegen/__init__.py
pytch/codegen/py3ast.py
pytch/containers.py
pytch/cstquery.py
pytch/errors.py
pytch/fuzz.py
pytch/greencst.py
pytch/lexer.py
pytch/parser.py
pytch/redcst.py
pytch/repl.py
pytch/syntax_tree.txt
pytch/typesystem/__init__.py
pytch/typesystem/builtins.py
pytch/typesystem/judgments.py
pytch/typesystem/reason.py
pytch/typesystem/typecheck.py
pytch/typesystem/types.py
pytch/utils.py
pytch-0.0.1.dist-info/entry_points.txt
pytch-0.0.1.dist-info/WHEEL
pytch-0.0.1.dist-info/METADATA
pytch-0.0.1.dist-info/RECORD
